a3t/__init__.py
a3t/utils.py
a3t/DSL/__init__.py
a3t/DSL/general_HotFlip.py
a3t/DSL/transformation.py
a3t/DSL/unittest.py
a3t/dataset/__init__.py
a3t/dataset/dataset_loader.py
a3t/dataset/download.py
a3t/dataset/en.key
a3t/dataset/sst2test.txt
a3t/diffai/__init__.py
a3t/diffai/__main__.py
a3t/diffai/ai.py
a3t/diffai/components.py
a3t/diffai/convert.py
a3t/diffai/exhaustive.py
a3t/diffai/goals.py
a3t/diffai/helpers.py
a3t/diffai/models.py
a3t/diffai/scheduling.py
a3t/diffai/train.py
tests/__init__.py
tests/test_run.py
a3t-0.0.1.dist-info/LICENSE
a3t-0.0.1.dist-info/METADATA
a3t-0.0.1.dist-info/WHEEL
a3t-0.0.1.dist-info/top_level.txt
a3t-0.0.1.dist-info/RECORD
